constprotocol/__init__.py
constprotocol/_list.py
constprotocol/_mapping.py
constprotocol/_set.py
constprotocol-0.0.1.dist-info/LICENSE
constprotocol-0.0.1.dist-info/METADATA
constprotocol-0.0.1.dist-info/WHEEL
constprotocol-0.0.1.dist-info/top_level.txt
constprotocol-0.0.1.dist-info/RECORD
