Metadata-Version: 2.1
Name: constprotocol
Version: 0.0.1
Summary: UNKNOWN
Home-page: UNKNOWN
Author: Dylan Baker
Author-email: dylan@pnwbakers.com
License: Apache Software License
Keywords: typing,immutable
Platform: UNKNOWN
Classifier: Development Status :: 3 - Alpha
Classifier: Intended Audience :: Developers
Classifier: License :: OSI Approved :: Apache Software License
Classifier: Programming Language :: Python :: 3 :: Only
Classifier: Programming Language :: Python :: 3.6
Classifier: Programming Language :: Python :: 3.7
Classifier: Programming Language :: Python :: 3.8
Classifier: Typing :: Typed
Requires-Python: >=3.6
Requires-Dist: typing-extensions ; python_version < "3.8"
